jange/__init__.py
jange/apps/__init__.py
jange/apps/topic.py
jange/base.py
jange/config.py
jange/ops/__init__.py
jange/ops/base.py
jange/ops/classify.py
jange/ops/cluster.py
jange/ops/dim.py
jange/ops/neighbors.py
jange/ops/stream.py
jange/ops/text/__init__.py
jange/ops/text/clean.py
jange/ops/text/embedding.py
jange/ops/text/encode.py
jange/ops/text/extract.py
jange/ops/topic.py
jange/ops/utils.py
jange/stream/__init__.py
jange/stream/stream.py
jange/vis/__init__.py
jange/vis/cluster.py
jange-0.1.7.dist-info/LICENSE
jange-0.1.7.dist-info/WHEEL
jange-0.1.7.dist-info/METADATA
jange-0.1.7.dist-info/RECORD
