Metadata-Version: 2.1
Name: jange
Version: 0.1.7
Summary: Easy NLP library for Python
Home-page: https://github.com/jangedoo/jange
License: Apache-2.0
Keywords: nlp,text processing,text analytics
Author: Sanjaya Subedi
Author-email: jangedoo@gmail.com
Requires-Python: >=3.6.1,<4.0.0
Classifier: License :: OSI Approved :: Apache Software License
Classifier: Programming Language :: Python :: 3
Classifier: Programming Language :: Python :: 3.7
Classifier: Programming Language :: Python :: 3.8
Classifier: Programming Language :: Python :: 3.9
Provides-Extra: docs
Requires-Dist: cytoolz (>=0.10.0,<0.11.0)
Requires-Dist: jsonschema (>=3.2.0,<4.0.0)
Requires-Dist: more_itertools (>=8.4.0,<9.0.0)
Requires-Dist: networkx (>=2.4,<3.0)
Requires-Dist: pandas (>=1.0.5,<2.0.0)
Requires-Dist: plotly (>=4.8.2,<5.0.0)
Requires-Dist: scikit-learn (>=0.23.1,<0.24.0)
Requires-Dist: spacy (>=2.2.0,<3.0.0)
Project-URL: Repository, https://github.com/jangedoo/jange
